ddrescue/__init__.py
ddrescue/bad_files/__init__.py
ddrescue/bad_files/backend.py
ddrescue/bad_files/file.py
ddrescue/bad_files/backends/pycdlib.py
ddrescue_bad_files-0.1.0.dist-info/licenses/LICENSE.AGPLv3
ddrescue_bad_files-0.1.0.dist-info/METADATA
ddrescue_bad_files-0.1.0.dist-info/WHEEL
ddrescue_bad_files-0.1.0.dist-info/entry_points.txt
ddrescue_bad_files-0.1.0.dist-info/top_level.txt
ddrescue_bad_files-0.1.0.dist-info/RECORD
