Metadata-Version: 2.4
Name: ddrescue-bad-files
Version: 0.1.0
Summary: Correlates file system data to bad block data from GNU ddrescue map files
Author-email: Matheus Afonso Martins Moreira <matheus@matheusmoreira.com>
Maintainer-email: Matheus Afonso Martins Moreira <matheus@matheusmoreira.com>
License-Expression: AGPL-3.0-or-later
Project-URL: Homepage, https://github.com/matheusmoreira/ddrescue-bad-files
Project-URL: Repository, https://github.com/matheusmoreira/ddrescue-bad-files.git
Project-URL: Issues, https://github.com/matheusmoreira/ddrescue-bad-files/issues
Keywords: bad blocks,bad sectors,ddrescue,GNU ddrescue,rescue,corruption,filesystem,image
Classifier: Development Status :: 4 - Beta
Classifier: Environment :: Console
Classifier: Intended Audience :: Developers
Classifier: Intended Audience :: Information Technology
Classifier: Intended Audience :: System Administrators
Classifier: Intended Audience :: Other Audience
Classifier: Natural Language :: English
Classifier: Operating System :: OS Independent
Classifier: Programming Language :: Python :: 3
Classifier: Programming Language :: Python :: 3 :: Only
Classifier: Topic :: System
Classifier: Topic :: System :: Filesystems
Classifier: Topic :: System :: Archiving :: Backup
Classifier: Topic :: System :: Archiving :: Mirroring
Classifier: Topic :: Utilities
Classifier: Topic :: Other/Nonlisted Topic
License-File: LICENSE.AGPLv3
Requires-Dist: intervaltree>=3.1.0
Requires-Dist: pycdlib>=1.14.0
Dynamic: license-file
